automatic_signature_sheet/__init__.py
automatic_signature_sheet/__main__.py
automatic_signature_sheet/generator.py
automatic_signature_sheet/latex_templates/default.tex
automatic_signature_sheet/latex_templates/no-id.tex
automatic_signature_sheet/latex_templates/rank.tex
automatic_signature_sheet/reader.py
automatic_signature_sheet-0.1.0.dist-info/METADATA
automatic_signature_sheet-0.1.0.dist-info/WHEEL
automatic_signature_sheet-0.1.0.dist-info/entry_points.txt
automatic_signature_sheet-0.1.0.dist-info/licenses/LICENSE
automatic_signature_sheet-0.1.0.dist-info/RECORD
