Metadata-Version: 2.4
Name: automatic-signature-sheet
Version: 0.1.0
Summary: A tool to automate printing signature sheets.
License-Expression: MIT
License-File: LICENSE
Keywords: signature,latex
Author: Yoann Piétri
Author-email: Yoann.Pietri@lip6.fr
Requires-Python: >=3.13
Classifier: Programming Language :: Python :: 3
Classifier: Programming Language :: Python :: 3.13
Classifier: Programming Language :: Python :: 3.14
Requires-Dist: jinja2 (>=3.1.6,<4.0.0)
Project-URL: Repository, https://github.com/nanoy42/yass
